aiorinnai/__init__.py
aiorinnai/api.py
aiorinnai/aws_srp.py
aiorinnai/client.py
aiorinnai/const.py
aiorinnai/device.py
aiorinnai/errors.py
aiorinnai/user.py
aiorinnai-0.3.5.dist-info/LICENSE
aiorinnai-0.3.5.dist-info/METADATA
aiorinnai-0.3.5.dist-info/WHEEL
aiorinnai-0.3.5.dist-info/top_level.txt
aiorinnai-0.3.5.dist-info/zip-safe
aiorinnai-0.3.5.dist-info/RECORD
