Metadata-Version: 2.1
Name: aiorinnai
Version: 0.3.5
Summary: Python interface for Rinnai Control-R API
Home-page: https://github.com/explosivo22/aio-rinnaicontrolr
Author: Brad Barbour
Author-email: barbourbj@gmail.com
License: Apache Software License
Keywords: rinnai,home automation,water heater
Classifier: Programming Language :: Python :: 3
Classifier: License :: OSI Approved :: Apache Software License
Classifier: Operating System :: OS Independent
License-File: LICENSE
Requires-Dist: aiohttp>=3.7.0
Requires-Dist: aioboto3==13.3.0
